satcfe/__init__.py
satcfe/alertas.py
satcfe/base.py
satcfe/clientelocal.py
satcfe/clientesathub.py
satcfe/entidades.py
satcfe/excecoes.py
satcfe/rede.py
satcfe/util.py
satcfe/resposta/__init__.py
satcfe/resposta/associarassinatura.py
satcfe/resposta/ativarsat.py
satcfe/resposta/cancelarultimavenda.py
satcfe/resposta/consultarnumerosessao.py
satcfe/resposta/consultarstatusoperacional.py
satcfe/resposta/consultarultimasessaofiscal.py
satcfe/resposta/enviardadosvenda.py
satcfe/resposta/extrairlogs.py
satcfe/resposta/padrao.py
satcfe/resposta/testefimafim.py
satcfe-2.2.dist-info/LICENSE
satcfe-2.2.dist-info/METADATA
satcfe-2.2.dist-info/WHEEL
satcfe-2.2.dist-info/top_level.txt
satcfe-2.2.dist-info/RECORD
