Metadata-Version: 2.1
Name: satcfe
Version: 2.2
Summary: Abstração do acesso ao equipamento SAT (SAT-CF-e)
Home-page: https://github.com/base4sistemas/satcfe
Author: Daniel Gonçalves
Author-email: daniel@base4.com.br
License: Apache Software License
Platform: any
Classifier: Development Status :: 5 - Production/Stable
Classifier: Environment :: Other Environment
Classifier: Intended Audience :: Developers
Classifier: Intended Audience :: Information Technology
Classifier: License :: OSI Approved :: Apache Software License
Classifier: Natural Language :: Portuguese (Brazilian)
Classifier: Operating System :: OS Independent
Classifier: Programming Language :: Python
Classifier: Programming Language :: Python :: 2.7
Classifier: Programming Language :: Python :: 3.6
Classifier: Programming Language :: Python :: 3.7
Classifier: Programming Language :: Python :: 3.8
Classifier: Programming Language :: Python :: 3.9
Classifier: Topic :: Office/Business :: Financial :: Point-Of-Sale
Classifier: Topic :: Software Development :: Libraries :: Python Modules
Classifier: Topic :: Utilities
Requires-Dist: cerberus (<2,>=1)
Requires-Dist: future
Requires-Dist: satcomum (>=2.2)
Requires-Dist: six
Requires-Dist: unidecode
Provides-Extra: sathub
Requires-Dist: requests ; extra == 'sathub'
